nkutils/__init__.py
nkutils/utils.py
nkutils-0.1.2.dist-info/METADATA
nkutils-0.1.2.dist-info/WHEEL
nkutils-0.1.2.dist-info/top_level.txt
nkutils-0.1.2.dist-info/RECORD
