Metadata-Version: 2.4
Name: nkutils
Version: 0.1.2
Summary: Simple Utilities for reading from excel named ranges, forward rates and other minor tasks
Author-email: Nikos Katrakis <nikosandthepython@gmail.com>
Requires-Dist: numpy
Requires-Dist: pandas
Requires-Dist: openpyxl
